{"visual":{"name":"analyticsTracker","displayName":"analyticsTracker","guid":"analyticsTrackerF4774A1BF3E6427B9543C75FD0C7516E","visualClassName":"Visual","version":"1.0.1","description":"Tracker for Google Analytics","supportUrl":"https://github.com/kulltc/pbi-ga","gitHubUrl":"https://github.com/kulltc/pbi-ga"},"apiVersion":"2.6.0","author":{"name":"Sven Witteveen","email":"svenwitteveen@gmail.com"},"assets":{"icon":"assets/icon.png"},"externalJS":null,"style":"style/visual.less","capabilities":"capabilities.json","dependencies":null,"stringResources":[]}
